postal_coder_jp/__init__.py
postal_coder_jp/postal_coder.py
postal_coder_jp-0.1.7.dist-info/LICENSE
postal_coder_jp-0.1.7.dist-info/METADATA
postal_coder_jp-0.1.7.dist-info/WHEEL
postal_coder_jp-0.1.7.dist-info/top_level.txt
postal_coder_jp-0.1.7.dist-info/RECORD
