Metadata-Version: 2.1
Name: postal-coder-jp
Version: 0.1.7
Summary: postal_coder_jp is a Python module for geocoding Japanese postal codes.
Home-page: https://pickerlab.net
Author: picker.
Author-email: hikaru.tokuhara@chionanthus.jp
License: MIT
License-File: LICENSE
